{"title":"CGV ─ 이벤트 ─ CGV 극장별","url":"http://www.cgv.co.kr/culture-event/event/defaultNew.aspx?mCode=005","favicon":"http://www.cgv.co.kr/culture-event/event/favicon.ico","elements":[{"title":"CGV DRIVE IN 곤지암","contents":"2021.10.21~2021.12.21","retrieved":1636578635398,"image":"https://img.cgv.co.kr/WebApp/contents/eventV4/33129/16348072800980.jpg"},{"title":"[왕십리] 러브어페어 보고\r\n크루와플과 엽서세트 받자!","contents":"2021.11.10~2021.11.14<span> . </span><em>D-3</em>","retrieved":1636578635400,"image":"https://img.cgv.co.kr/WebApp/contents/eventV4/33440/16365277456620.jpg"},{"title":"[백신패스관] 운영 가이드","contents":"","retrieved":1636578635401,"image":"https://img.cgv.co.kr/WebApp/contents/eventV4/33377/16358348681300.png"},{"title":"[아네트] 포스터 3종\r\n증정 이벤트!","contents":"2021.11.09~2021.11.13<span> . </span><em>D-2</em>","link":"http://www.cgv.co.kr/culture-event/event/detailViewUnited.aspx?seq=33427&menu=005","retrieved":1636528437152,"image":"https://img.cgv.co.kr/WebApp/contents/eventV4/33427/16364471289870.jpg"},{"title":"[퍼스트카우]\r\n굿즈 증정 이벤트","contents":"2021.11.09~2021.11.14<span> . </span><em>D-3</em>","retrieved":1636578635402,"image":"https://img.cgv.co.kr/WebApp/contents/eventV4/33425/16364429761110.jpg"},{"title":"[의정부태흥]\r\n쿠팡이츠 주문 시 선물 증정","contents":"2021.11.09~2021.12.09","retrieved":1636578635403,"image":"https://img.cgv.co.kr/WebApp/contents/eventV4/33418/16364165542460.jpg"},{"title":"11월 인사이터 특강\r\n알잘딱깔센","contents":"2021.11.08~2021.11.26","retrieved":1636578635404,"image":"https://img.cgv.co.kr/WebApp/contents/eventV4/33414/16363518530130.jpg"},{"title":"씨네드쉐프 SNS \r\n친구 추가 이벤트","contents":"2021.11.08~2021.11.14<span> . </span><em>D-3</em>","retrieved":1636578635405,"image":"https://img.cgv.co.kr/WebApp/contents/eventV4/33413/16363514838390.jpg"},{"title":"러브어페어\r\n명씨네 굿즈 패키지","contents":"2021.11.08~2021.11.14<span> . </span><em>D-3</em>","retrieved":1636578635409,"image":"https://img.cgv.co.kr/WebApp/contents/eventV4/33410/16363476917170.jpg"}]}