{"title":"익스트림무비 ─ 시사회 ─ 시사회진행","url":"https://extmovie.com/sisaing","favicon":"https://extmovie.com/favicon.ico","elements":[{"title":"'고스트버스터즈 라이즈&#03...","contents":"영화 &lt;고스트버스터즈 라이즈&gt; 시사회에 초대합니다. 꼭 참석하고 게시판에 후기...","link":"https://extmovie.com/sisaing/70066290","retrieved":1636352324189,"image":"https://extmovie.com/files/thumbnails/290/066/070/295x295.crop.jpg?20211108142748"},{"title":"블랙필즈 2번째 작품 'The P...","contents":"온라인 숏폼 플랫폼 '블랙필즈' 2번째 작품 &lt;The Pet Killer&gt; 온라인 시사회에 ...","link":"https://extmovie.com/sisaing/70066048","retrieved":1636352324190,"image":"https://extmovie.com/files/thumbnails/048/066/070/295x295.crop.jpg?20211108143417"},{"title":"'소설가 구보의 하루' ...","contents":"영화 &lt;소설가 구보의 하루&gt; 시사회에 초대합니다. 꼭 참석하고 게시판에 후기 남...","link":"https://extmovie.com/sisaing/70056761","retrieved":1636332271301,"image":"https://extmovie.com/files/thumbnails/761/056/070/295x295.crop.jpg?20211108082643"},{"title":"'라임크라임' 시사회에...","contents":"영화 &lt;라임크라임&gt; 시사회에 초대합니다. 꼭 참석하고 게시판에 후기 남겨주실 ...","link":"https://extmovie.com/sisaing/70056727","retrieved":1636332271302,"image":"https://extmovie.com/files/thumbnails/727/056/070/295x295.crop.jpg?20211108082655"},{"title":"'나의 끝, 당신의 시작&#039...","contents":"영화 &lt;나의 끝, 당신의 시작&gt; 언론 배급 시사회에 초대합니다. 평일 오후에 진행...","link":"https://extmovie.com/sisaing/69947426","retrieved":1636002863078,"image":"https://extmovie.com/files/thumbnails/426/947/069/295x295.crop.jpg?20211104132804"},{"title":"'장르만 로맨스' 익스...","contents":"영화 &lt;장르만 로맨스&gt; 익스트림무비 단독관 GV 시사회에 초대합니다. 꼭 참석하...","link":"https://extmovie.com/sisaing/69942748","retrieved":1635993264873,"image":"https://extmovie.com/files/thumbnails/748/942/069/295x295.crop.jpg?20211104112648"},{"title":"마블 '이터널스' 리뷰 ...","contents":"마블 영화 &lt;이터널스&gt; 리뷰 이벤트입니다. 관람 후 나만의 추천 포인트를 영화수...","link":"https://extmovie.com/sisaing/69893730","retrieved":1635904644770,"image":"https://extmovie.com/files/thumbnails/730/893/069/295x295.crop.jpg?20211103100359"},{"title":"마블 '이터널스' 돌비 ...","contents":"","link":"https://extmovie.com/sisaing/69893046","retrieved":1635900237142,"image":"https://extmovie.com/files/thumbnails/046/893/069/295x295.crop.jpg?20211103100600"},{"title":"시사회, 이벤트 당첨 확률 올리는 법","contents":"시사회,예매권,경품등 통합해서 당첨확률을 올리는 팁입니다 일단 당첨자 비율 -...","link":"https://extmovie.com/sisaing/10382475","retrieved":1633810455555,"image":"https://extmovie.com/files/thumbnails/475/382/010/295x295.crop.jpg?20210417161650"}]}