{"title":"메가박스 ─ 이벤트 ─ 시사회 무대인사","url":"https://www.megabox.co.kr/event/curtaincall","favicon":"https://www.megabox.co.kr/event/favicon.ico","elements":[{"title":"<더 문> 개봉일 무대인사","contents":"2023.08.02 ~ 2023.08.02","link":"https://www.megabox.co.kr/event/curtaincall#","retrieved":1683609398519,"image":"https://img.megabox.co.kr/SharedImg/event/2023/07/21/97ohGhh3zppIeZN8wsH3Z17WLQbaFiIf.jpg"},{"title":"<극장판 슈퍼윙스: 맥시멈 스피드> 2주차 무대인사","contents":"2023.07.30 ~ 2023.07.30","link":"https://www.megabox.co.kr/event/curtaincall#","retrieved":1683609398519,"image":"https://img.megabox.co.kr/SharedImg/event/2023/07/21/suNYjikNcGITGpO4VxPrMhxyW15o3Bb3.jpg"},{"title":"<더 문> 스페셜 무대인사","contents":"2023.07.30 ~ 2023.07.30","link":"https://www.megabox.co.kr/event/curtaincall#","retrieved":1683609398519,"image":"https://img.megabox.co.kr/SharedImg/event/2023/07/18/Wf2EPBt9xeWWyVIj2rMfGZny5SJj5qiy.jpg"},{"title":"<밀수> 더위사냥 무대인사","contents":"2023.07.29 ~ 2023.07.30","link":"https://www.megabox.co.kr/event/curtaincall#","retrieved":1683609398519,"image":"https://img.megabox.co.kr/SharedImg/event/2023/07/19/SpkJVU1qS0kyculkq1X8OGuxWT2mHRYr.jpg"},{"title":"<극장판 슈퍼윙스: 맥시멈 스피드> 무대인사","contents":"2023.07.23 ~ 2023.07.23","link":"https://www.megabox.co.kr/event/curtaincall#","retrieved":1683609398519,"image":"https://img.megabox.co.kr/SharedImg/event/2023/07/17/4nAbyXUj4IYUyq3lfrHoNVfJcQVxFcUe.jpg"},{"title":"<밀수> 스페셜 무대인사","contents":"2023.07.23 ~ 2023.07.23","link":"https://www.megabox.co.kr/event/curtaincall#","retrieved":1683609398519,"image":"https://img.megabox.co.kr/SharedImg/event/2023/07/10/0lxAaUGEkTFEaN9bVKIiB3zchX7PMj7i.jpg"},{"title":"<비공식작전> 개봉전 무대인사","contents":"2023.07.22 ~ 2023.07.23","link":"https://www.megabox.co.kr/event/curtaincall#","retrieved":1683609398519,"image":"https://img.megabox.co.kr/SharedImg/event/2023/07/17/Ib8sqtceW6TY2iG7Lwmbvj5kY9c3nSoB.jpg"},{"title":"<더 문> 메가박스 회원 시사회","contents":"2023.07.21 ~ 2023.07.26","link":"https://www.megabox.co.kr/event/curtaincall#","retrieved":1683609398519,"image":"https://img.megabox.co.kr/SharedImg/event/2023/07/21/059UjSeiDZdc0EJrgp85DKMOsTvrsjlZ.jpg"},{"title":"<달짝지근해: 7510> 메가박스 회원시사회","contents":"2023.07.20 ~ 2023.08.03","link":"https://www.megabox.co.kr/event/curtaincall#","retrieved":1683609398519,"image":"https://img.megabox.co.kr/SharedImg/event/2023/07/20/sJGOSUWylacNyqgu37Xzx2LicJtiHoUj.jpg"},{"title":"<콘트리트 유토피아> 메가박스 회원 시사회","contents":"2023.07.19 ~ 2023.07.30","link":"https://www.megabox.co.kr/event/curtaincall#","retrieved":1683609398519,"image":"https://img.megabox.co.kr/SharedImg/event/2023/07/19/3DukuaPjYWJMzCaBzCBFENCk79UN5E77.jpg"}]}