{"title":"메가박스 ─ 이벤트 ─ 시사회 무대인사","url":"https://www.megabox.co.kr/event/curtaincall","favicon":"https://www.megabox.co.kr/event/favicon.ico","elements":[{"title":"<범죄도시3> 2주차 무대인사","contents":"2023.06.10 ~ 2023.06.11","link":"https://www.megabox.co.kr/event/curtaincall#","retrieved":1683609398519,"image":"https://img.megabox.co.kr/SharedImg/event/2023/06/01/nk80URyJhZbCZkzn920ZZ0Sys0EyNI8e.jpg"},{"title":"<자우림, 더 원더랜드> 개봉주 무대인사","contents":"2023.06.07 ~ 2023.06.11","link":"https://www.megabox.co.kr/event/curtaincall#","retrieved":1683609398519,"image":"https://img.megabox.co.kr/SharedImg/event/2023/06/02/m4v8Rpt0kbPD4tyQ8qTXwifpFd2NRxf5.png"},{"title":"<엔니오: 더 마에스트로> 메가박스 필름/클래식 소사이어티 회원시사","contents":"2023.05.30 ~ 2023.06.13","link":"https://www.megabox.co.kr/event/curtaincall#","retrieved":1683609398519,"image":"https://img.megabox.co.kr/SharedImg/event/2023/05/30/VV9uUseHLCux9BCoDjf9ZmVkHfHCanxC.jpg"}]}